rye_easy/__init__.py
rye_easy-0.1.29.dist-info/METADATA
rye_easy-0.1.29.dist-info/WHEEL
rye_easy-0.1.29.dist-info/entry_points.txt
rye_easy-0.1.29.dist-info/RECORD
